<?xml version="1.1" encoding="UTF-8"?>
<databaseChangeLog 
    xmlns="http://www.liquibase.org/xml/ns/dbchangelog"
    xmlns:ext="http://www.liquibase.org/xml/ns/dbchangelog-ext"
    xmlns:xsi="http://www.w3.org/2001/XMLSchema-instance"
    xsi:schemaLocation="http://www.liquibase.org/xml/ns/dbchangelog-ext 
        http://www.liquibase.org/xml/ns/dbchangelog/dbchangelog-ext.xsd 
        http://www.liquibase.org/xml/ns/dbchangelog 
        http://www.liquibase.org/xml/ns/dbchangelog/dbchangelog-4.1.xsd">

	<changeSet id="f_apply_backward_compatibility_macro-function" author="${default_author}" runOnChange="true">
		<createProcedure 
			procedureName="f_apply_backward_compatibility_macro" 
			dbms="postgresql" 
			path="f_apply_backward_compatibility_macro.sql" 
			relativeToChangelogFile="true"/>
		<rollback/>
	</changeSet>
	
	<changeSet id="f_sys_obj_definition-function" author="${default_author}" runOnChange="true">
		<createProcedure 
			procedureName="f_sys_obj_definition" 
			dbms="postgresql" 
			path="f_sys_obj_definition.sql" 
			relativeToChangelogFile="true"/>
		<rollback/>
	</changeSet>

	<changeSet id="f_sys_obj_dependency-function" author="${default_author}" runOnChange="true">
		<createProcedure 
			procedureName="f_sys_obj_dependency" 
			dbms="postgresql" 
			path="f_sys_obj_dependency.sql" 
			relativeToChangelogFile="true"/>
		<rollback/>
	</changeSet>

	<changeSet id="f_sys_obj_drop_command-function" author="${default_author}" runOnChange="true">
		<createProcedure 
			procedureName="f_sys_obj_drop_command" 
			dbms="postgresql" 
			path="f_sys_obj_drop_command.sql" 
			relativeToChangelogFile="true"/>
		<rollback/>
	</changeSet>
        	        	
	<changeSet id="f_meta_view_dependency_level-function" author="${default_author}" runOnChange="true">
		<createProcedure 
			procedureName="f_meta_view_dependency_level" 
			dbms="postgresql" 
			path="f_meta_view_dependency_level.sql" 
			relativeToChangelogFile="true"/>
		<rollback/>
	</changeSet>
	
	<changeSet id="f_meta_view_name-function" author="${default_author}" runOnChange="true">
		<createProcedure 
			procedureName="f_meta_view_name" 
			dbms="postgresql" 
			path="f_meta_view_name.sql" 
			relativeToChangelogFile="true"/>
		<rollback/>
	</changeSet>
	
	<changeSet id="f_meta_view_id-function" author="${default_author}" runOnChange="true">
		<createProcedure 
			procedureName="f_meta_view_id" 
			dbms="postgresql" 
			path="f_meta_view_id.sql" 
			relativeToChangelogFile="true"/>
		<rollback/>
	</changeSet>
	
	<changeSet id="f_table_partitions-function" author="${default_author}" runOnChange="true">
		<createProcedure 
			procedureName="f_table_partitions" 
			dbms="postgresql" 
			path="f_table_partitions.sql" 
			relativeToChangelogFile="true"/>
		<rollback/>
	</changeSet>
	
</databaseChangeLog>
